retriever_elsa/__init__.py
retriever_elsa/retriever_pipeline.py
retriever_elsa-0.18.dist-info/METADATA
retriever_elsa-0.18.dist-info/WHEEL
retriever_elsa-0.18.dist-info/top_level.txt
retriever_elsa-0.18.dist-info/RECORD
