Metadata-Version: 2.1
Name: retriever-elsa
Version: 0.18
Summary: A package for interacting with Qdrant for memory retrieval and upsert operations
Author: abubakar
Author-email: abubakarilyas624@gmail.com
Classifier: Programming Language :: Python :: 3
Classifier: License :: OSI Approved :: MIT License
Classifier: Operating System :: OS Independent
Requires-Python: >=3.6
